vectorfieldviz/__init__.py
vectorfieldviz/analysis.py
vectorfieldviz/utils.py
vectorfieldviz/visualization2d.py
vectorfieldviz/visualization3d.py
vectorfieldviz-3.1.4.dist-info/licenses/LICENSE
vectorfieldviz-3.1.4.dist-info/METADATA
vectorfieldviz-3.1.4.dist-info/WHEEL
vectorfieldviz-3.1.4.dist-info/top_level.txt
vectorfieldviz-3.1.4.dist-info/RECORD
